collective.volto.slimheader-2.0.0-py3.11-nspkg.pth
collective/volto/slimheader/__init__.py
collective/volto/slimheader/configure.zcml
collective/volto/slimheader/interfaces.py
collective/volto/slimheader/permissions.zcml
collective/volto/slimheader/setuphandlers.py
collective/volto/slimheader/testing.py
collective/volto/slimheader/browser/__init__.py
collective/volto/slimheader/browser/configure.zcml
collective/volto/slimheader/browser/overrides/.gitkeep
collective/volto/slimheader/browser/static/.gitkeep
collective/volto/slimheader/controlpanel/__init__.py
collective/volto/slimheader/controlpanel/configure.zcml
collective/volto/slimheader/controlpanel/slimheader.py
collective/volto/slimheader/locales/README.rst
collective/volto/slimheader/locales/__init__.py
collective/volto/slimheader/locales/collective.volto.slimheader.pot
collective/volto/slimheader/locales/update.py
collective/volto/slimheader/locales/update.sh
collective/volto/slimheader/locales/en/LC_MESSAGES/collective.volto.slimheader.po
collective/volto/slimheader/locales/it/LC_MESSAGES/collective.volto.slimheader.po
collective/volto/slimheader/profiles/default/browserlayer.xml
collective/volto/slimheader/profiles/default/catalog.xml
collective/volto/slimheader/profiles/default/controlpanel.xml
collective/volto/slimheader/profiles/default/metadata.xml
collective/volto/slimheader/profiles/default/rolemap.xml
collective/volto/slimheader/profiles/default/registry/main.xml
collective/volto/slimheader/profiles/default/registry/slimheader.xml
collective/volto/slimheader/profiles/uninstall/browserlayer.xml
collective/volto/slimheader/restapi/__init__.py
collective/volto/slimheader/restapi/configure.zcml
collective/volto/slimheader/restapi/deserializers/__init__.py
collective/volto/slimheader/restapi/deserializers/configure.zcml
collective/volto/slimheader/restapi/deserializers/slimheader.py
collective/volto/slimheader/restapi/serializers/__init__.py
collective/volto/slimheader/restapi/serializers/configure.zcml
collective_volto_slimheader-2.0.0.dist-info/LICENSE.GPL
collective_volto_slimheader-2.0.0.dist-info/LICENSE.rst
collective_volto_slimheader-2.0.0.dist-info/METADATA
collective_volto_slimheader-2.0.0.dist-info/WHEEL
collective_volto_slimheader-2.0.0.dist-info/entry_points.txt
collective_volto_slimheader-2.0.0.dist-info/namespace_packages.txt
collective_volto_slimheader-2.0.0.dist-info/top_level.txt
collective_volto_slimheader-2.0.0.dist-info/RECORD
